<annotation>
	<folder>frames</folder>
	<filename>frame_1220.jpg</filename>
	<path>/home/PIDS/Desktop/Anotaciones_Sergio/167/frames/frame_1220.jpg</path>
	<source>
		<database>Unknown</database>
	</source>
	<size>
		<width>1280</width>
		<height>720</height>
		<depth>3</depth>
	</size>
	<segmented>0</segmented>
	<object>
		<name>robot</name>
		<pose>Unspecified</pose>
		<truncated>0</truncated>
		<difficult>0</difficult>
		<bndbox>
			<xmin>609</xmin>
			<ymin>260</ymin>
			<xmax>915</xmax>
			<ymax>660</ymax>
		</bndbox>
	</object>
	<object>
		<name>robot</name>
		<pose>Unspecified</pose>
		<truncated>0</truncated>
		<difficult>0</difficult>
		<bndbox>
			<xmin>847</xmin>
			<ymin>353</ymin>
			<xmax>918</xmax>
			<ymax>414</ymax>
		</bndbox>
	</object>
</annotation>
